
[
  {
    "level": "1",
    "title": "Crystal palace   [14Light]",
    "artist": "SHIKI obj.vectorla movie:Nyu",
    "comment": "",
    "md5": "282450efa8c62a3000aa7eddb89345d5",
    "url_diff": ""
  },
  {
    "level": "1",
    "title": "DEATH SENTENCE [DP HYPER]",
    "artist": "kohaxy obj.vectorla",
    "comment": "譜面同梱",
    "md5": "3ef8999c24e86b94c59637c356d3a1f7",
    "url_diff": ""
  },
  {
    "level": "1",
    "title": "MOBILYS  [14keys BASIC]",
    "artist": "Dachs obj.vectorla",
    "comment": "",
    "md5": "4617dfa8be6b4c264d2521f8baec58d7",
    "url_diff": ""
  },
  {
    "level": "1",
    "title": "Together [OTONETHER]",
    "artist": "pan obj.OTONE",
    "comment": "",
    "md5": "95da0d0261f5c9b232902332c7a066f5",
    "url_diff": ""
  },
  {
    "level": "1",
    "title": "Disordered Moon [DPH]",
    "artist": "raii obj.vectorla",
    "comment": "",
    "md5": "e551fcc983945273bd047a7d2e735ac1",
    "url_diff": ""
  },
  {
    "level": "1",
    "title": "恋色エモーション -Another-",
    "artist": "こはのん(kohaxy vs Hanon) obj.vectorla",
    "comment": "",
    "md5": "e6c1a858a068733b5b1d00ccce6bcaea",
    "url_diff": ""
  },
  {
    "level": "1",
    "title": "Ocean Memory  [Type/B]",
    "artist": "Junk/obj.vectorla",
    "comment": "",
    "md5": "b8a93e44caa4241483d7c2925a0d0469",
    "url_diff": ""
  },
  {
    "level": "1",
    "title": "Yellow Smile (bms edit) [Type/C]",
    "artist": "Junk/obj.vectorla",
    "comment": "",
    "md5": "026f296cce13d477697343cac030dfa2",
    "url_diff": ""
  },
  {
    "level": "1",
    "title": "私のヒトミ [Type/B]",
    "artist": "nmk feat.橘花音/obj.vectorla",
    "comment": "",
    "md5": "a56558102f3afda8a1b3a426e4dbfc64",
    "url_diff": ""
  },
  {
    "level": "2",
    "title": "Yellow Smile (bms edit) [Type/D]",
    "artist": "Junk/obj.vectorla",
    "comment": "発狂難易度表",
    "md5": "56fb2939e516dbf5585a00334668b32f",
    "url_diff": ""
  },
  {
    "level": "2",
    "title": "On And On!! [14keys]",
    "artist": "ETIA. feat. Jenga Movie: わっふゑ/obj.vectorla",
    "comment": "",
    "md5": "efd7b0775d33b3ba31edf479d6b20d22",
    "url_diff": ""
  },
  {
    "level": "2",
    "title": "Function Generator (DP Another)",
    "artist": "kohaxy obj.桜音音",
    "comment": "譜面同梱",
    "md5": "11eff40ac61fd7e7de3443f213285b05",
    "url_diff": ""
  },
  {
    "level": "2",
    "title": "Longinus  [DP ANOTHER]",
    "artist": "琥珀 obj.vectorla",
    "comment": "譜面同梱",
    "md5": "6d7ade6286745dbcbd9bf70e5ca380fc",
    "url_diff": ""
  },
  {
    "level": "2",
    "title": "Dahlia [Type/B]",
    "artist": "琥珀/obj.vectorla",
    "comment": "",
    "md5": "ed11db511a100190896d74c382381335",
    "url_diff": ""
  },
  {
    "level": "2",
    "title": "Yellow Smile (bms edit) [Type/D]",
    "artist": "Junk/obj.vectorla",
    "comment": "発狂難易度表",
    "md5": "56fb2939e516dbf5585a00334668b32f",
    "url_diff": ""
  },
  {
    "level": "2",
    "title": "A BEAUTIFUL WINGS [Type/B]",
    "artist": "SHIKI/obj.vectorla",
    "comment": "",
    "md5": "04d4c52b46b439f5a2f1edc9c825e498",
    "url_diff": ""
  },
  {
    "level": "2",
    "title": "私のヒトミ [Type/A]",
    "artist": "nmk feat.橘花音/obj.vectorla",
    "comment": "",
    "md5": "53f2c54705d588b293fd68bda8d73e23",
    "url_diff": ""
  },
  {
    "level": "2",
    "title": "Rosario -AnotherStory-  [TypeA]",
    "artist": "SB YUNE/obj vectorla",
    "comment": "",
    "md5": "457c424b1be4c8acc5519056a5a0c344",
    "url_diff": ""
  },
  {
    "level": "3",
    "title": "Coda  [DPA]",
    "artist": "mossari obj.vectorla",
    "comment": "",
    "md5": "dbd3fdc4454e13faa62d2c8dafa65c55",
    "url_diff": "https://drive.google.com/file/d/0B8LMHvFHiG2PbUpxT21rR003V0U/view?resourcekey=0-jF466hA7Zi7k6Z4FyBAC1Q"
  },
  {
    "level": "3",
    "title": "シンフォニックライツ [HYPER]",
    "artist": "Est feat. 雪歌ユフ obj.vectorla",
    "comment": "satellite",
    "md5": "bfa7329f23edce8d84f146018c220717",
    "url_diff": ""
  },
  {
    "level": "3",
    "title": "Contrail  -ANOTHER-",
    "artist": "RIN obj.vectorla",
    "comment": "",
    "md5": "fd8ce260db8e5b1b23b13b2742448d2e",
    "url_diff": ""
  },
  {
    "level": "3",
    "title": "Rosario -AnotherStory- [TypeB]",
    "artist": "SB YUNE/obj vectorla",
    "comment": "",
    "md5": "36b7e94100277b094ab74af38e7e3c24",
    "url_diff": ""
  },
  {
    "level": "4",
    "title": "霖風 [DP HYPER]",
    "artist": "薄荷堂 龍 vs. futonbound obj.vectorla",
    "comment": "satellite",
    "md5": "395811c489090c3e648d2385995de94c",
    "url_diff": "https://drive.google.com/file/d/1yFU1Lh_HPXxf905ypfX2TBd92v4pPi-K/view?usp=sharing"
  },
  {
    "level": "4",
    "title": "Aerial artS  [14keysLN]",
    "artist": "e.m.u obj.vectorla",
    "comment": "",
    "md5": "c697222432da6f2231c7152ba637ccc1",
    "url_diff": ""
  },
  {
    "level": "4",
    "title": "恋愛サーキュレーション [ぴよぴよ]",
    "artist": "Sengoku Nadeko obj.vectorla",
    "comment": "",
    "md5": "3230bcf61ba13dedca3f9898435295a8",
    "url_diff": ""
  },
  {
    "level": "4",
    "title": "Summer Sunset [EXTRA VER.C]",
    "artist": "Lollipop / obj.vectorla",
    "comment": "",
    "md5": "877fe2310fce9ec0c1614fd8278e4141",
    "url_diff": ""
  },
  {
    "level": "4",
    "title": "-生命の樹- [BASIC]",
    "artist": "SOMON obj.vectorla",
    "comment": "",
    "md5": "cc2eb45c1972fb1f62210d58cdb557cd",
    "url_diff": ""
  },
  {
    "level": "4",
    "title": "IKAROS  [DPH]",
    "artist": "ETIA. feat. Jenga Movie: HDLV obj.vectorla",
    "comment": "",
    "md5": "b5c6fdbc8b0bc1db92f1b88229c24968",
    "url_diff": ""
  },
  {
    "level": "4",
    "title": "私のヒトミ [Type/C]",
    "artist": "nmk feat.橘花音/obj.vectorla",
    "comment": "",
    "md5": "ce980829577e611b606b4d5f3ed69db1",
    "url_diff": ""
  },
  {
    "level": "5",
    "title": "Orion [14keys]",
    "artist": "nya_n/obj.vectorla obj.vectorla",
    "comment": "",
    "md5": "76c1f2aad6d5fd889b99aaba4149daa2",
    "url_diff": "https://drive.google.com/file/d/1-N7rT7b88en8nlL8cSReM-31071H1m-z/view?usp=sharing"
  },
  {
    "level": "5",
    "title": "シンフォニックライツ [ANOTHER]",
    "artist": "Est feat. 雪歌ユフ obj.vectorla",
    "comment": "",
    "md5": "0b2135787803d5c6b6e8a9c73f92cfbb",
    "url_diff": ""
  },
  {
    "level": "5",
    "title": "彼女なのか  [U.N.Owen]",
    "artist": "しらいし obj.vectorla",
    "comment": "",
    "md5": "038731e97cca3ebf0906a9d003d7fc00",
    "url_diff": ""
  },
  {
    "level": "5",
    "title": "Terpsichore [Type/A]",
    "artist": "Jun Kuroda obj.vectorla",
    "comment": "",
    "md5": "836e3ecc5fd131c954284ae788a6d67f",
    "url_diff": ""
  },
  {
    "level": "6",
    "title": "take me to the moon  [DP]",
    "artist": "uma feat. ましろ obj.vectorla",
    "comment": "",
    "md5": "f10e229a05bc70ebeb5e3ef0d14d5052",
    "url_diff": ""
  },
  {
    "level": "6",
    "title": "Function Generator (DP Insane)",
    "artist": "kohaxy obj.桜音音",
    "comment": "譜面同梱",
    "md5": "73c88839f7c7d1e1a263ecbbb6ff4902",
    "url_diff": ""
  },
  {
    "level": "7",
    "title": "Crystal palace   [14Plus]",
    "artist": "SHIKI obj.vectorla movie:Nyu",
    "comment": "発狂難易度表",
    "md5": "5b911957a5f920ef8871599ced312872",
    "url_diff": ""
  },
  {
    "level": "7",
    "title": "ozma [DP v1]",
    "artist": "TJ.hangneil vs Jackz reobj.vectorla",
    "comment": "",
    "md5": "cf0a335e0d44566f56bbcfca29ecae95",
    "url_diff": ""
  },
  {
    "level": "7",
    "title": "Repeat⇔Again [DP]",
    "artist": "Qayo feat.美島愛音 mov:140/fth obj.vectorla",
    "comment": "",
    "md5": "dbe029b59b47b72855fef082c5b489c5",
    "url_diff": ""
  },
  {
    "level": "7",
    "title": "Summer Sunset [EXTRA VER.D]",
    "artist": "Lollipop / obj.vectorla",
    "comment": "",
    "md5": "7222b535ad02616c3477e6d917a4c772",
    "url_diff": ""
  },
  {
    "level": "7",
    "title": "KANPAI!!!　 (ソフドリ)",
    "artist": "EUROBE Sound Team”謎の揚力” and setuna obj.shirahu",
    "comment": "",
    "md5": "86e7e3252fb66509a9bed5233e6af469",
    "url_diff": ""
  },
  {
    "level": "7",
    "title": "Driving Wind  [DOUBLE WIND]",
    "artist": "p_d /obj. SSVD",
    "comment": "",
    "md5": "1839758b0edccf150db32f90204984fc",
    "url_diff": ""
  },
  {
    "level": "7",
    "title": "Pleiades East West Mass Rapid Transit Line [ANOTHER]",
    "artist": "Kaname Shigeyoshi / obj. SSVD",
    "comment": "",
    "md5": "e73a760a3b46336265489c8cf4fb0189",
    "url_diff": ""
  },
  {
    "level": "7",
    "title": "[OpenMRF]COSMO TRAVEL [SUPERCLUSTER]",
    "artist": "Reanisz×minun♂ obj.vectorla",
    "comment": "",
    "md5": "040077ba38277b2e8dbb43b244bda752",
    "url_diff": ""
  },
  {
    "level": "8",
    "title": "Snowdin Town",
    "artist": "Toby Fox obj.vectorla",
    "comment": "",
    "md5": "b630f4e9293c06b697740678a01268ff",
    "url_diff": ""
  },
  {
    "level": "8",
    "title": "Fluctuation [98%keys]",
    "artist": "Electro Controller / obj.vectorla",
    "comment": "",
    "md5": "ef3cd7621afae2432ac2e6614724b91d",
    "url_diff": ""
  },
  {
    "level": "8",
    "title": "Searching For A Guiding Light  [ANOTHER]",
    "artist": "Kyuzo Sameura/obj.vectorla",
    "comment": "",
    "md5": "97406ee97e0a2d2db5020e2757fbf0e7",
    "url_diff": ""
  },
  {
    "level": "8",
    "title": "-生命の樹- [EXPERT]",
    "artist": "SOMON obj.vectorla",
    "comment": "",
    "md5": "ff7b213ca66fcae45466d41cbf1ba03b",
    "url_diff": ""
  },
  {
    "level": "8",
    "title": "-終天-　 [そら]",
    "artist": "SOMON obj.天傘",
    "comment": "",
    "md5": "da7295f2c9d2625687da00370626dd49",
    "url_diff": ""
  },
  {
    "level": "8",
    "title": "XIII Charlotte -ⅩⅣKEYS-",
    "artist": "m108/Notes:天乃桜音々 BGA:メツヤ Illust:flap",
    "comment": "",
    "md5": "fdf7ead9d221a8372ca8468fada32bd1",
    "url_diff": ""
  },
  {
    "level": "8",
    "title": "Jack Knife [Another Murder]",
    "artist": "kohaxy obj.vectorla",
    "comment": "発狂難易度表",
    "md5": "f0b2bacc636002f743bc458ee90b9a5c",
    "url_diff": ""
  },
  {
    "level": "9",
    "title": "霖風 [DP ANOTHER]",
    "artist": "薄荷堂 龍 vs. futonbound obj.vectorla",
    "comment": "",
    "md5": "b7b2c9e506436799263a6c7bf896647b",
    "url_diff": "https://drive.google.com/file/d/1yFU1Lh_HPXxf905ypfX2TBd92v4pPi-K/view?usp=sharing"
  },
  {
    "level": "9",
    "title": "美しく逝きたい [DP]",
    "artist": "Situation VS KEI obj.vectorla",
    "comment": "",
    "md5": "f214be67a87ddc49372d59af040f4436",
    "url_diff": ""
  },
  {
    "level": "9",
    "title": "Crystal palace   [14EX]",
    "artist": "SHIKI obj.vectorla movie:Nyu",
    "comment": "",
    "md5": "d3aa65dbba1ebae9bd428559f9fb7209",
    "url_diff": ""
  },
  {
    "level": "9",
    "title": "MOBILYS [14keys ver.A]",
    "artist": "Dachs obj.vectorla",
    "comment": "",
    "md5": "eb2b5819d9bdda83d833055f16c0dde7",
    "url_diff": ""
  },
  {
    "level": "9",
    "title": "恋愛サーキュレーション [なでこスネイク]",
    "artist": "Sengoku Nadeko obj.vectorla",
    "comment": "",
    "md5": "9a22a618edbe32494abd4472bfaa524b",
    "url_diff": ""
  },
  {
    "level": "9",
    "title": "-Phantom Tear-［ANOTHER］",
    "artist": "SOMON / obj.vectorla",
    "comment": "譜面同梱",
    "md5": "985e26ab42e0272e701269d1950e8449",
    "url_diff": ""
  },
  {
    "level": "9",
    "title": "Disordered Moon [DPA]",
    "artist": "raii obj.vectorla",
    "comment": "",
    "md5": "a787a09f9103358e7c579d5d1b525dac",
    "url_diff": ""
  },
  {
    "level": "10",
    "title": "Orion [★★]",
    "artist": "nya_n/obj.vectorla",
    "comment": "",
    "md5": "93ab4309e96aad5269e2883b60fbbb2f",
    "url_diff": "https://drive.google.com/file/d/1-N7rT7b88en8nlL8cSReM-31071H1m-z/view?usp=sharing"
  },
  {
    "level": "21",
    "title": "XIII Charlotte -INFINITY KEYS-",
    "artist": "m108/Notes:天乃桜音々 BGA:メツヤ Illust:flap",
    "comment": "",
    "md5": "2b44efdc91e18af9adb6c8a15eba6be0",
    "url_diff": ""
  },
  {
    "level": "21",
    "title": "美しく逝きたい [DP I've]",
    "artist": "Situation VS KEI obj.vectorla",
    "comment": "",
    "md5": "0e278efe111d0a730995c21c026b5dff",
    "url_diff": ""
  },
  {
    "level": "21",
    "title": "DEATH SENTENCE [DP ANOTHER]",
    "artist": "kohaxy obj.vectorla",
    "comment": "譜面同梱",
    "md5": "351d3ae85b63e92385984b304fbeeb6b",
    "url_diff": ""
  },
  {
    "level": "21",
    "title": "take me to the moon  [DP LUNATIC]",
    "artist": "uma feat. ましろ obj.vectorla",
    "comment": "",
    "md5": "82ae8099e33caf057bd13363a627b3ec",
    "url_diff": ""
  },
  {
    "level": "23",
    "title": "Pleiades East West Mass Rapid Transit Line [INSANE]",
    "artist": "Kaname Shigeyoshi / obj. SSVD",
    "comment": "",
    "md5": "3bc07fc119095bff75fb507fafd0daaf",
    "url_diff": ""
  },
  {
    "level": "25",
    "title": "ozma [DP v2]",
    "artist": "TJ.hangneil vs Jackz reobj.vectorla",
    "comment": "",
    "md5": "a6ef169bde2e51fbcde717a870d2b034",
    "url_diff": ""
  }
]
